{
  "posts": [
    {
      "id": 1,
      "title": "json-server",
      "author": "typicode"
    }
  ],
  "comments": [
    {
      "id": 1,
      "body": "some comment",
      "postId": 1
    }
  ],
  "profile": {
    "name": "typicode"
  },
  "costs": [
    {
      "date": "2022-02-18",
      "time": "16:04",
      "category": "Еда",
      "sum": "1200",
      "curency": "UAH",
      "comment": "",
      "transType": "costs",
      "id": 1
    },
    {
      "date": "2022-02-11",
      "time": "",
      "category": "Еда",
      "sum": "",
      "curency": "UAH",
      "comment": "",
      "transType": "costs",
      "id": 2
    }
  ],
  "incomes": []
}